Workbook

Sheet Income Tracker
A1: Date | B1: Client / Project | C1: Description | D1: Amount ($) | E1: Status | F1: Tax Set-Aside (30%) | G1: Notes
A2: 2026-08-01 | B2: Client A | C2: Landing page design | D2: 1200 | E2: Paid | F2: =D2*0.3
A3: 2026-08-05 | B3: Client B | C3: Consulting retainer | D3: 800 | E3: Paid | F3: =D3*0.3
A4: 2026-08-10 | B4: Client C | C4: Copywriting project | D4: 450 | E4: Invoiced | F4: =D4*0.3 | G4: Due Aug 24
A5: 2026-08-15 | C5: Template sale (Gumroad) | D5: 57 | E5: Paid | F5: =D5*0.3 | G5: 3 x $19
C8: TOTALS | D8: =SUM(D2:D100) | F8: =SUM(F2:F100)

Sheet Monthly Overview
A1: Month | B1: Income | C1: Expenses | D1: Profit | E1: Tax Reserve | F1: Take-Home
A2: January | C2: 0 | D2: =B2-C2 | E2: =B2*0.3 | F2: =D2-E2
A3: February | C3: 0 | D3: =B3-C3 | E3: =B3*0.3 | F3: =D3-E3
A4: March | C4: 0 | D4: =B4-C4 | E4: =B4*0.3 | F4: =D4-E4
A5: April | C5: 0 | D5: =B5-C5 | E5: =B5*0.3 | F5: =D5-E5
A6: May | C6: 0 | D6: =B6-C6 | E6: =B6*0.3 | F6: =D6-E6
A7: June | C7: 0 | D7: =B7-C7 | E7: =B7*0.3 | F7: =D7-E7
A8: July | C8: 0 | D8: =B8-C8 | E8: =B8*0.3 | F8: =D8-E8
A9: August | C9: 0 | D9: =B9-C9 | E9: =B9*0.3 | F9: =D9-E9
A10: September | C10: 0 | D10: =B10-C10 | E10: =B10*0.3 | F10: =D10-E10
A11: October | C11: 0 | D11: =B11-C11 | E11: =B11*0.3 | F11: =D11-E11
A12: November | C12: 0 | D12: =B12-C12 | E12: =B12*0.3 | F12: =D12-E12
A13: December | C13: 0 | D13: =B13-C13 | E13: =B13*0.3 | F13: =D13-E13

Sheet Expense Log
A1: Date | B1: Category | C1: Description | D1: Amount ($) | E1: Receipt

Sheet Tax Estimator
A1: Tax Estimator
A3: Total Income | B3: =SUM('Income Tracker'!D:D)
A4: Total Expenses | B4: =SUM('Expense Log'!D:D)
A5: Net Income | B5: =B3-B4
A6: Est. Tax Rate | B6: 0.3
A7: Est. Tax (30%) | B7: =B5*B6
A8: Already Set Aside | B8: =SUM('Income Tracker'!F:F)
A9: Remaining to Pay | B9: =B7-B8

Sheet Feast or Famine
A1: Monthly Income Visualization
A2: Check this chart when a slow month makes you panic. Patterns repeat. February is always slow. March picks up.
A4: January | B4: ='Monthly Overview'!B3
A5: February | B5: ='Monthly Overview'!B4
A6: March | B6: ='Monthly Overview'!B5
A7: April | B7: ='Monthly Overview'!B6
A8: May | B8: ='Monthly Overview'!B7
A9: June | B9: ='Monthly Overview'!B8
A10: July | B10: ='Monthly Overview'!B9
A11: August | B11: ='Monthly Overview'!B10
A12: September | B12: ='Monthly Overview'!B11
A13: October | B13: ='Monthly Overview'!B12
A14: November | B14: ='Monthly Overview'!B13
A15: December | B15: ='Monthly Overview'!B14
